README.md
setup.py
cerebro_ml.egg-info/PKG-INFO
cerebro_ml.egg-info/SOURCES.txt
cerebro_ml.egg-info/dependency_links.txt
cerebro_ml.egg-info/requires.txt
cerebro_ml.egg-info/top_level.txt
nn/__init__.py
nn/layers/__init__.py